odoo/addons/survey_question_type_binary/README.rst
odoo/addons/survey_question_type_binary/__init__.py
odoo/addons/survey_question_type_binary/__manifest__.py
odoo/addons/survey_question_type_binary/i18n/it.po
odoo/addons/survey_question_type_binary/i18n/survey_question_type_binary.pot
odoo/addons/survey_question_type_binary/models/__init__.py
odoo/addons/survey_question_type_binary/models/survey_question.py
odoo/addons/survey_question_type_binary/models/survey_user_input.py
odoo/addons/survey_question_type_binary/models/survey_user_input_line.py
odoo/addons/survey_question_type_binary/models/survey_user_input_line_binary.py
odoo/addons/survey_question_type_binary/readme/CONFIGURE.rst
odoo/addons/survey_question_type_binary/readme/CONTRIBUTORS.rst
odoo/addons/survey_question_type_binary/readme/DESCRIPTION.rst
odoo/addons/survey_question_type_binary/security/ir.model.access.csv
odoo/addons/survey_question_type_binary/static/description/icon.png
odoo/addons/survey_question_type_binary/static/description/index.html
odoo/addons/survey_question_type_binary/static/src/js/survey_form.js
odoo/addons/survey_question_type_binary/templates/survey_template.xml
odoo/addons/survey_question_type_binary/tests/__init__.py
odoo/addons/survey_question_type_binary/tests/test_survey.py
odoo/addons/survey_question_type_binary/views/survey_question.xml
odoo/addons/survey_question_type_binary/views/survey_user_input_line.xml
odoo14_addon_survey_question_type_binary-14.0.1.0.1.dev26.dist-info/METADATA
odoo14_addon_survey_question_type_binary-14.0.1.0.1.dev26.dist-info/WHEEL
odoo14_addon_survey_question_type_binary-14.0.1.0.1.dev26.dist-info/top_level.txt
odoo14_addon_survey_question_type_binary-14.0.1.0.1.dev26.dist-info/RECORD
